swap/__init__.py
swap/api/__init__.py
swap/api/clients.py
swap/api/commands.py
swap/api/datasets.py
swap/api/filters.py
swap/api/hooks.py
swap/api/models.py
swap/api/parsers.py
swap/api/polling.py
swap/api/schemas.py
swap/api/services.py
swap/api/state.py
swap/api/steps.py
swap/api/requests/__init__.py
swap/api/requests/builders.py
swap/api/sequences/__init__.py
swap/api/sequences/builders.py
swap/api/sequences/step_codes.py
swap/common/__init__.py
swap/common/config.py
swap/common/filters.py
swap/common/logging.py
swap/common/models.py
swap/common/parsers.py
swap/common/schemas.py
swap/common/utils.py
swap/common/validators.py
swap/common/static/__init__.py
swap/common/static/schemas/__init__.py
swap/common/static/schemas/execution_completion.json
swap/common/static/schemas/execution_failure.json
swap/common/static/schemas/execution_request.json
swap/common/static/schemas/execution_request_accept.json
swap/common/static/schemas/execution_request_cancel.json
swap/common/static/schemas/execution_request_decline.json
swap/common/static/schemas/execution_status_update.json
swap/common/static/schemas/headers.json
swap/common/static/schemas/offer_execution_request.json
swap/common/static/schemas/service_discovery.json
swap/common/static/schemas/service_discovery_response.json
swap/common/static/schemas/service_offering.json
swap/common/static/schemas/service_request.json
swap/messaging/__init__.py
swap/messaging/actions.py
swap/messaging/callbacks.py
swap/messaging/clients.py
swap/messaging/exceptions.py
swap/messaging/handlers.py
swap/messaging/identities.py
swap/messaging/listeners.py
swap/messaging/models.py
swap/messaging/parsers.py
swap/messaging/registries.py
swap/messaging/schemas.py
swap/messaging/messages/__init__.py
swap/messaging/messages/builders.py
swap/service/__init__.py
swap/service/datasets.py
swap/service/developer_helper.py
swap/service/env.py
swap/service/generate_config.py
swap/service/get_started.py
swap/service/swap_service.py
swap_python_sdk-0.2.3.dist-info/METADATA
swap_python_sdk-0.2.3.dist-info/WHEEL
swap_python_sdk-0.2.3.dist-info/top_level.txt
swap_python_sdk-0.2.3.dist-info/RECORD
